chipcutter/__init__.py
chipcutter/_version.py
chipcutter-0.0.1.dist-info/METADATA
chipcutter-0.0.1.dist-info/WHEEL
chipcutter-0.0.1.dist-info/licenses/LICENSE
chipcutter-0.0.1.dist-info/RECORD
