Metadata-Version: 2.1
Name: chipcutter
Version: 0.0.1
Summary: Split tensors in batches and merge back predictions
Project-URL: Homepage, https://github.com/dzanaga/chipcutter
Author: Daniele Zanaga
License-File: LICENSE
Classifier: License :: OSI Approved :: MIT License
Classifier: Operating System :: OS Independent
Classifier: Programming Language :: Python :: 3
Requires-Python: >=3.7
Requires-Dist: numpy
